MANIFEST.in
README.md
requirements-test.txt
requirements.txt
setup.py
punctuator/__init__.py
punctuator/convert_to_readable.py
punctuator/data.py
punctuator/demo_play_with_model.py
punctuator/error_calculator.py
punctuator/main.py
punctuator/main2.py
punctuator/models.py
punctuator/play_with_model.py
punctuator/punc.py
punctuator/tests.py
punctuator.egg-info/PKG-INFO
punctuator.egg-info/SOURCES.txt
punctuator.egg-info/dependency_links.txt
punctuator.egg-info/entry_points.txt
punctuator.egg-info/not-zip-safe
punctuator.egg-info/requires.txt
punctuator.egg-info/top_level.txt