Metadata-Version: 2.1
Name: punctuator
Version: 0.9.3
Summary: Adds punctuation to a block of text.
Home-page: https://github.com/chrisspen/punctuator
Author: Chris Spencer
Author-email: chrisspen@gmail.com
License: MIT
Platform: UNKNOWN
Classifier: Development Status :: 4 - Beta
Classifier: Intended Audience :: Developers
Classifier: License :: OSI Approved :: MIT License
Classifier: Operating System :: OS Independent
Classifier: Programming Language :: Python
Classifier: Programming Language :: Python :: 3.6
Classifier: Programming Language :: Python :: 3.7
